metacode/__init__.py
metacode/building.py
metacode/comment.py
metacode/errors.py
metacode/parsing.py
metacode/py.typed
metacode/typing.py
metacode-0.0.4.dist-info/LICENSE
metacode-0.0.4.dist-info/METADATA
metacode-0.0.4.dist-info/WHEEL
metacode-0.0.4.dist-info/top_level.txt
metacode-0.0.4.dist-info/RECORD
